async_weave/__init__.py
async_weave/py.typed
async_weave/weaver.py
async_weave-0.1.1.dist-info/METADATA
async_weave-0.1.1.dist-info/WHEEL
async_weave-0.1.1.dist-info/top_level.txt
async_weave-0.1.1.dist-info/RECORD
