Metadata-Version: 2.2
Name: async-weave
Version: 0.1.1
Summary: An asynchronous task manager that handles concurrent task execution with automatic retries, status monitoring, and graceful cancellation.
Requires-Python: >=3.12
